MANIFEST.in
README.md
requirements.txt
setup.py
vba_wrapper/__init__.py
vba_wrapper/cheat.py
vba_wrapper/core.py
vba_wrapper/exceptions.py
vba_wrapper/registers.py
vba_wrapper.egg-info/PKG-INFO
vba_wrapper.egg-info/SOURCES.txt
vba_wrapper.egg-info/dependency_links.txt
vba_wrapper.egg-info/requires.txt
vba_wrapper.egg-info/top_level.txt