Metadata-Version: 1.1
Name: vba-wrapper
Version: 0.0.3
Summary: wrapper for the VBA emulator
Home-page: https://github.com/kanzure/python-vba-wrapper
Author: Bryan Bishop
Author-email: kanzure@gmail.com
License: BSD
Platform: any
Classifier: License :: OSI Approved :: BSD License
Classifier: Topic :: Software Development :: Libraries :: Python Modules
Classifier: Programming Language :: Python
Classifier: Programming Language :: Python :: 2.7
